django_features/__init__.py
django_features/apps.py
django_features/custom_fields/__init__.py
django_features/custom_fields/admin.py
django_features/custom_fields/apps.py
django_features/custom_fields/fields.py
django_features/custom_fields/migrations/0001_initial.py
django_features/custom_fields/migrations/0002_make_custom_field_label_and_value_text_translateable.py
django_features/custom_fields/migrations/0003_add_type_filter_to_fields.py
django_features/custom_fields/migrations/0004_remove_mutiple_choice_field.py
django_features/custom_fields/migrations/0005_rename_text_to_label.py
django_features/custom_fields/migrations/0006_add_filterable_to_customfield.py
django_features/custom_fields/migrations/__init__.py
django_features/custom_fields/migrations/max_migration.txt
django_features/custom_fields/models/__init__.py
django_features/custom_fields/models/base.py
django_features/custom_fields/models/field.py
django_features/custom_fields/models/value.py
django_features/custom_fields/routers.py
django_features/custom_fields/serializers.py
django_features/custom_fields/translation.py
django_features/custom_fields/viewsets.py
django_features/fields.py
django_features/locale/de/LC_MESSAGES/django.po
django_features/locale/en/LC_MESSAGES/django.po
django_features/locale/fr/LC_MESSAGES/django.po
django_features/pagination.py
django_features/serializers.py
django_features/settings/__init__.py
django_features/settings/fields.py
django_features/system_message/__init__.py
django_features/system_message/admin.py
django_features/system_message/apps.py
django_features/system_message/forms.py
django_features/system_message/management/__init__.py
django_features/system_message/management/commands/__init__.py
django_features/system_message/management/commands/create_default_system_message_types.py
django_features/system_message/migrations/0001_add_system_message_model.py
django_features/system_message/migrations/0002_create_default_system_message_types.py
ftw_django_features-2025.6.1.dist-info/LICENSE
ftw_django_features-2025.6.1.dist-info/METADATA
ftw_django_features-2025.6.1.dist-info/WHEEL
ftw_django_features-2025.6.1.dist-info/RECORD
