Metadata-Version: 2.3
Name: ftw-django-features
Version: 2025.6.1
Summary: A collection of features used in our Django-based web applications.
Author: 4teamwork AG
Requires-Python: >=3.12,<4
Classifier: Programming Language :: Python :: 3
Classifier: Programming Language :: Python :: 3.12
Classifier: Programming Language :: Python :: 3.13
Requires-Dist: django (>=4.2,<5.0)
Requires-Dist: django-click (>=2,<3)
Requires-Dist: django-configurations (>=2,<3)
Requires-Dist: django-constance (>=4,<5)
Requires-Dist: django-extensions (>=4,<5)
Requires-Dist: django-filter (>=25,<26)
Requires-Dist: django-linear-migrations (>=2,<3)
Requires-Dist: django-modeltranslation (>=0.19,<0.20)
Requires-Dist: djangorestframework (>=3,<4)
Requires-Dist: pluck (>=0.2,<0.3)
Requires-Dist: python-dotenv (>=1,<2)
Requires-Dist: pytz (>=2025.2,<2026.0)
